django_thumbor/__init__.py
django_thumbor/conf.py
django_thumbor/templatetags/__init__.py
django_thumbor/templatetags/thumbor_tags.py
hmtvltk2_django_thumbor-1.0.2.dist-info/LICENSE
hmtvltk2_django_thumbor-1.0.2.dist-info/METADATA
hmtvltk2_django_thumbor-1.0.2.dist-info/WHEEL
hmtvltk2_django_thumbor-1.0.2.dist-info/top_level.txt
hmtvltk2_django_thumbor-1.0.2.dist-info/RECORD
