Metadata-Version: 2.1
Name: hmtvltk2-django-thumbor
Version: 1.0.2
Summary: A django application to resize images using the thumbor service
Home-page: http://github.com/hmtvltk2/django-thumbor/
Author: Enrico Batista da Luz
Author-email: rico.bl@gmail.com
License: django-thumbor is licensed under the MIT license. For more information, please see LICENSE file.
Classifier: License :: OSI Approved :: MIT License
License-File: LICENSE
Requires-Dist: Django (>=2.2)
Requires-Dist: libthumbor (>=1.2.0)
